odoo/addons/web_widget_char_size/README.rst
odoo/addons/web_widget_char_size/__init__.py
odoo/addons/web_widget_char_size/__manifest__.py
odoo/addons/web_widget_char_size/i18n/it.po
odoo/addons/web_widget_char_size/i18n/web_widget_char_size.pot
odoo/addons/web_widget_char_size/readme/CONTRIBUTERS.rst
odoo/addons/web_widget_char_size/readme/DESCRIPTION.rst
odoo/addons/web_widget_char_size/static/description/icon.png
odoo/addons/web_widget_char_size/static/description/index.html
odoo/addons/web_widget_char_size/static/src/js/char_widget.esm.js
odoo_addon_web_widget_char_size-16.0.1.0.0.3.dist-info/METADATA
odoo_addon_web_widget_char_size-16.0.1.0.0.3.dist-info/WHEEL
odoo_addon_web_widget_char_size-16.0.1.0.0.3.dist-info/top_level.txt
odoo_addon_web_widget_char_size-16.0.1.0.0.3.dist-info/RECORD
